{
    "classname": "FormHeader",
    "definitions": {
        "apis": {
            "custom": [],
            "passthrough": []
        },
        "events": {
            "custom": [],
            "passthrough": [
                {
                    "access": "Enable",
                    "group": "General",
                    "kuid": "ece266e66d3b4fb283a6be91f0062797",
                    "originalPropertyKey": "onClick",
                    "propertyIndex": 1,
                    "propertyKey": "onClick",
                    "pw": {
                        "access": "readwrite",
                        "category": "action",
                        "displayName": "onClick",
                        "srcWidget": "btnBack",
                        "type": "action",
                        "uiRepresentation": "Label-Label-Button-Button",
                        "wType": "Button"
                    },
                    "srcWgtKUID": "hdaf855988d444eb8bd1e31cb5453e6b"
                }
            ]
        },
        "groups": {
            "apis": [],
            "events": [],
            "properties": [],
            "widgets": []
        },
        "properties": {
            "custom": [],
            "passthrough": [
                {
                    "access": "Enable",
                    "group": "General",
                    "kuid": "ha18c12b92f0478cb20e644961c2c79f",
                    "originalPropertyKey": "text",
                    "propertyIndex": 1,
                    "propertyKey": "text",
                    "pw": {
                        "access": "readwrite",
                        "category": "look",
                        "dependentKeysKUIDs": null,
                        "displayName": "Text",
                        "srcWidget": "lblHeading",
                        "type": "string",
                        "uiRepresentation": "Label-Textbox",
                        "wType": "Label"
                    },
                    "srcWgtKUID": "h47e440845944365adf9207628c5b2d0"
                },
                {
                    "access": "Enable",
                    "group": "General",
                    "kuid": "d3a5d493d7cf4aa388054bbcd2bff8b2",
                    "originalPropertyKey": "src",
                    "propertyIndex": 2,
                    "propertyKey": "src",
                    "pw": {
                        "access": "readwrite",
                        "category": "widget",
                        "dependentKeysKUIDs": null,
                        "displayName": "Source",
                        "srcWidget": "imgBack",
                        "type": "string",
                        "uiConfig": {
                            "Button": {
                                "dataRetrieverId": "Imagelist",
                                "dataUpdaterId": "Imagelist",
                                "popupId": "Imagelist",
                                "type": "ImageEditBtn"
                            },
                            "Label": {}
                        },
                        "uiRepresentation": "Label-Label-Button",
                        "wType": "Image"
                    },
                    "srcWgtKUID": "d67abf66872449479779c555e9a3be32"
                },
                {
                    "access": "Enable",
                    "group": "General",
                    "kuid": "a2c41305ee06499d898d4917034fb9fa",
                    "originalPropertyKey": "width",
                    "propertyIndex": 3,
                    "propertyKey": "width1",
                    "pw": {
                        "access": "readwrite",
                        "category": "look",
                        "defaultValue": {
                            "type": "string",
                            "value": ""
                        },
                        "dependentKeysKUIDs": null,
                        "displayName": "Back btn Width",
                        "forkablePlatforms": {
                            "desktop": [
                                "desktopweb",
                                "kiosk"
                            ],
                            "mobile": [
                                "iphone",
                                "android",
                                "winphone8",
                                "spaip",
                                "spaan",
                                "spawinphone8",
                                "spabb"
                            ],
                            "tablet": [
                                "ipad",
                                "android",
                                "windows8",
                                "spaipad",
                                "spaandroidtablet",
                                "spawindowstablet"
                            ]
                        },
                        "srcWidget": "flxBack",
                        "type": "object",
                        "uiConfig": {
                            "Combobox": {
                                "masterData": [
                                    [
                                        "Dp",
                                        "dp"
                                    ],
                                    [
                                        "Px",
                                        "px"
                                    ],
                                    [
                                        "%",
                                        "%"
                                    ],
                                    [
                                        "Default",
                                        "Default"
                                    ],
                                    [
                                        "Preferred",
                                        "preferred"
                                    ]
                                ]
                            },
                            "Label": {},
                            "Textbox": {}
                        },
                        "uiRepresentation": "Label-Textbox-Combobox",
                        "wType": "FlexContainer"
                    },
                    "srcWgtKUID": "a1130dcb15744fed8f7184bd63da4fd5"
                },
                {
                    "access": "Enable",
                    "group": "General",
                    "kuid": "bdf75958989840e1a6fa23b31144cd94",
                    "originalPropertyKey": "width",
                    "propertyIndex": 4,
                    "propertyKey": "width2",
                    "pw": {
                        "access": "readwrite",
                        "category": "look",
                        "defaultValue": {
                            "type": "string",
                            "value": ""
                        },
                        "dependentKeysKUIDs": null,
                        "displayName": "Heading Width",
                        "forkablePlatforms": {
                            "desktop": [
                                "desktopweb",
                                "kiosk"
                            ],
                            "mobile": [
                                "iphone",
                                "android",
                                "winphone8",
                                "spaip",
                                "spaan",
                                "spawinphone8",
                                "spabb"
                            ],
                            "tablet": [
                                "ipad",
                                "android",
                                "windows8",
                                "spaipad",
                                "spaandroidtablet",
                                "spawindowstablet"
                            ]
                        },
                        "srcWidget": "flxHeading",
                        "type": "object",
                        "uiConfig": {
                            "Combobox": {
                                "masterData": [
                                    [
                                        "Dp",
                                        "dp"
                                    ],
                                    [
                                        "Px",
                                        "px"
                                    ],
                                    [
                                        "%",
                                        "%"
                                    ],
                                    [
                                        "Default",
                                        "Default"
                                    ],
                                    [
                                        "Preferred",
                                        "preferred"
                                    ]
                                ]
                            },
                            "Label": {},
                            "Textbox": {}
                        },
                        "uiRepresentation": "Label-Textbox-Combobox",
                        "wType": "FlexContainer"
                    },
                    "srcWgtKUID": "ac6dc5b9411c46e3a267713abf49e380"
                },
                {
                    "access": "Enable",
                    "group": "General",
                    "kuid": "c3b887f0c08e45b5bb00b3067e04b8f1",
                    "originalPropertyKey": "width",
                    "propertyIndex": 5,
                    "propertyKey": "width3",
                    "pw": {
                        "access": "readwrite",
                        "category": "look",
                        "defaultValue": {
                            "type": "string",
                            "value": ""
                        },
                        "dependentKeysKUIDs": null,
                        "displayName": "Logou tbtn Width",
                        "forkablePlatforms": {
                            "desktop": [
                                "desktopweb",
                                "kiosk"
                            ],
                            "mobile": [
                                "iphone",
                                "android",
                                "winphone8",
                                "spaip",
                                "spaan",
                                "spawinphone8",
                                "spabb"
                            ],
                            "tablet": [
                                "ipad",
                                "android",
                                "windows8",
                                "spaipad",
                                "spaandroidtablet",
                                "spawindowstablet"
                            ]
                        },
                        "srcWidget": "flxLogoutBtn",
                        "type": "object",
                        "uiConfig": {
                            "Combobox": {
                                "masterData": [
                                    [
                                        "Dp",
                                        "dp"
                                    ],
                                    [
                                        "Px",
                                        "px"
                                    ],
                                    [
                                        "%",
                                        "%"
                                    ],
                                    [
                                        "Default",
                                        "Default"
                                    ],
                                    [
                                        "Preferred",
                                        "preferred"
                                    ]
                                ]
                            },
                            "Label": {},
                            "Textbox": {}
                        },
                        "uiRepresentation": "Label-Textbox-Combobox",
                        "wType": "FlexContainer"
                    },
                    "srcWgtKUID": "b751342b0f2145ffa8b26040d561cbfb"
                },
                {
                    "access": "Enable",
                    "group": "General",
                    "kuid": "ac89b3c22d164879a63280add8db1521",
                    "originalPropertyKey": "isVisible",
                    "propertyIndex": 6,
                    "propertyKey": "isVisible1",
                    "pw": {
                        "access": "readwrite",
                        "category": "look",
                        "dependentKeysKUIDs": null,
                        "displayName": "Brand Visible",
                        "srcWidget": "lblBrand",
                        "type": "boolean",
                        "uiRepresentation": "Label-Radiobuttongroup",
                        "wType": "Label"
                    },
                    "srcWgtKUID": "id824140c95e41958be1c1fcbadae8e9"
                },
                {
                    "access": "Enable",
                    "group": "General",
                    "kuid": "hc63735bbfb94d1f8fe044e4d1981701",
                    "originalPropertyKey": "isVisible",
                    "propertyIndex": 7,
                    "propertyKey": "isVisible2",
                    "pw": {
                        "access": "readwrite",
                        "category": "look",
                        "dependentKeysKUIDs": null,
                        "displayName": "Img Visible",
                        "srcWidget": "imgBack",
                        "type": "boolean",
                        "uiRepresentation": "Label-Radiobuttongroup",
                        "wType": "Image"
                    },
                    "srcWgtKUID": "d67abf66872449479779c555e9a3be32"
                },
                {
                    "access": "Enable",
                    "group": "General",
                    "kuid": "ea32631d51aa4041ad441e6c9c0bc9d1",
                    "originalPropertyKey": "isVisible",
                    "propertyIndex": 8,
                    "propertyKey": "isVisible3",
                    "pw": {
                        "access": "readwrite",
                        "category": "look",
                        "dependentKeysKUIDs": null,
                        "displayName": "Btn Visible",
                        "srcWidget": "btnBack",
                        "toolTip": "Hides/shows the widget in the screen",
                        "type": "boolean",
                        "uiRepresentation": "Label-Radiobuttongroup",
                        "wType": "Button"
                    },
                    "srcWgtKUID": "hdaf855988d444eb8bd1e31cb5453e6b"
                }
            ]
        },
        "widgets": {
            "expose": [],
            "passthrough": []
        }
    },
    "namespace": "com.softserveinc",
    "version": "1.0.0"
}