{
    "AS_Button_e9ff83b78e734a0d94c206294f0aa099": {
        "id": "AS_Button_e9ff83b78e734a0d94c206294f0aa099",
        "type": "ACTION_SEQUENCE",
        "params": [{
            "datatype": "collection",
            "name": "eventobject"
        }],
        "contextObj": {
            "name": "frmLogin",
            "type": "forms",
            "platform": "",
            "KUID": "e158d89d96004277a5d5494ae3fef4c6"
        },
        "language": "js",
        "actions": [{
            "id": "INVOKE_FUNCTION___fd2a6663504e4f28b1b3107fb66f930d",
            "type": "INVOKE_FUNCTION",
            "sequenceKUID": "logOut",
            "display": "logOut",
            "inputparams": [],
            "parentId": null,
            "callbackType": null,
            "disabled": null,
            "source": "controller"
        }]
    }
}